woodchipper/__init__.py
woodchipper/configs.py
woodchipper/context.py
woodchipper/logger.py
woodchipper/processors.py
woodchipper/http/__init__.py
woodchipper/http/awslambda.py
woodchipper/http/fastapi.py
woodchipper/http/flask.py
woodchipper/monitors/__init__.py
woodchipper/monitors/sqlalchemy.py
woodchipper-0.14.0.dist-info/COPYING
woodchipper-0.14.0.dist-info/METADATA
woodchipper-0.14.0.dist-info/WHEEL
woodchipper-0.14.0.dist-info/top_level.txt
woodchipper-0.14.0.dist-info/RECORD
