Metadata-Version: 2.1
Name: woodchipper
Version: 0.14.0
Summary: Woodchipper is a support library for plugging structured logging into a Python project.
Author: Tackle.io, Inc.
License: MIT
Project-URL: Homepage, https://github.com/tackle-io/woodchipper
Project-URL: Documentation, https://tackle-io.github.io/woodchipper
Classifier: Development Status :: 4 - Beta
Classifier: License :: OSI Approved :: MIT License
Classifier: Environment :: Console
Classifier: Topic :: System :: Logging
Requires-Python: >=3.8
License-File: COPYING
Requires-Dist: structlog >=21.5.0
Provides-Extra: dev
Requires-Dist: build ; extra == 'dev'
Requires-Dist: twine ~=3.6.0 ; extra == 'dev'
Requires-Dist: pip-tools ~=6.4.0 ; extra == 'dev'
Requires-Dist: mkdocs ; extra == 'dev'
Requires-Dist: jinja2 <3.1.0 ; extra == 'dev'
Requires-Dist: pytest ; extra == 'dev'
Requires-Dist: flask ; extra == 'dev'
Requires-Dist: fastapi ; extra == 'dev'
Requires-Dist: httpx ; extra == 'dev'
Requires-Dist: SQLAlchemy <2 ; extra == 'dev'
Requires-Dist: structlog-sentry <2 ; extra == 'dev'
Requires-Dist: requests ; extra == 'dev'
Requires-Dist: tox ; extra == 'dev'
Provides-Extra: sentry
Requires-Dist: structlog-sentry <2.0.0 ; extra == 'sentry'
